setup.py
blessing_distributions/Binomialdistribution.py
blessing_distributions/Gaussiandistribution.py
blessing_distributions/Generaldistribution.py
blessing_distributions/__init__.py
blessing_distributions.egg-info/PKG-INFO
blessing_distributions.egg-info/SOURCES.txt
blessing_distributions.egg-info/dependency_links.txt
blessing_distributions.egg-info/not-zip-safe
blessing_distributions.egg-info/top_level.txt