Metadata-Version: 1.0
Name: blessing-distributions
Version: 0.1
Summary: Gaussian distributions
Home-page: UNKNOWN
Author: Guembe Blessing
Author-email: blessingodede@gmail.com
License: UNKNOWN
Platform: UNKNOWN
